fftlog/config.py
fftlog/fftlog.py
fftlog/jax_special.py
fftlog/module.py
fftlog/sbt.py
fftlog/utils.py
fftlog_lss-0.1.2.dist-info/licenses/LICENSE
fftlog_lss-0.1.2.dist-info/METADATA
fftlog_lss-0.1.2.dist-info/WHEEL
fftlog_lss-0.1.2.dist-info/top_level.txt
fftlog_lss-0.1.2.dist-info/RECORD
