Metadata-Version: 2.4
Name: fftlog-lss
Version: 0.1.2
Summary: JAX-accelerated FFTLog implementation for Large Scale Structure cosmology
Author: Pierre Zhang
Author-email: Pierre Zhang <pierre.zhang@example.com>
Maintainer-email: Pierre Zhang <pierre.zhang@example.com>
License-Expression: MIT
Project-URL: Homepage, https://github.com/pierrexyz/fftlog
Project-URL: Repository, https://github.com/pierrexyz/fftlog
Project-URL: Documentation, https://github.com/pierrexyz/fftlog#readme
Project-URL: Bug Tracker, https://github.com/pierrexyz/fftlog/issues
Keywords: fft,logarithmic,transform,scientific,numerical,jax,gpu,acceleration
Classifier: Development Status :: 3 - Alpha
Classifier: Intended Audience :: Science/Research
Classifier: Operating System :: OS Independent
Classifier: Environment :: Console
Classifier: Programming Language :: Python
Classifier: Programming Language :: Python :: 3
Classifier: Programming Language :: Python :: 3.8
Classifier: Programming Language :: Python :: 3.9
Classifier: Programming Language :: Python :: 3.10
Classifier: Programming Language :: Python :: 3.11
Classifier: Programming Language :: Python :: 3.12
Classifier: Topic :: Scientific/Engineering
Classifier: Topic :: Scientific/Engineering :: Mathematics
Classifier: Topic :: Scientific/Engineering :: Physics
Requires-Python: >=3.8
License-File: LICENSE
Requires-Dist: numpy>=1.20.0
Requires-Dist: scipy>=1.7.0
Provides-Extra: jax
Requires-Dist: jax>=0.4.0; extra == "jax"
Requires-Dist: jaxlib>=0.4.0; extra == "jax"
Requires-Dist: interpax>=0.3.0; extra == "jax"
Provides-Extra: dev
Requires-Dist: pytest>=6.0; extra == "dev"
Requires-Dist: pytest-cov>=2.0; extra == "dev"
Requires-Dist: black>=22.0; extra == "dev"
Requires-Dist: flake8>=4.0; extra == "dev"
Requires-Dist: mypy>=0.950; extra == "dev"
Provides-Extra: docs
Requires-Dist: sphinx>=4.0; extra == "docs"
Requires-Dist: sphinx-rtd-theme>=1.0; extra == "docs"
Requires-Dist: nbsphinx>=0.8; extra == "docs"
Dynamic: author
Dynamic: license-file
